lessline/__init__.py
lessline/text_file.py
src/__init__.py
src/text_file.py
tests/__init__.py
tests/test_text_file.py
lessline-0.1.0.dist-info/LICENSE
lessline-0.1.0.dist-info/METADATA
lessline-0.1.0.dist-info/WHEEL
lessline-0.1.0.dist-info/top_level.txt
lessline-0.1.0.dist-info/RECORD
